deltatorch/__init__.py
deltatorch/deltadataset.py
deltatorch/id_based_deltadataset.py
deltatorch/pytorch.py
deltatorch/skip_batch_deltadataset.py
deltatorch-0.0.3.dist-info/METADATA
deltatorch-0.0.3.dist-info/WHEEL
deltatorch-0.0.3.dist-info/RECORD
