Metadata-Version: 2.1
Name: deltatorch
Version: 0.0.3
Summary: DeltaTorch allows loading training data from  DeltaLake tables for training Deep Learning models using PyTorch
Home-page: https://github.com/mshtelma/deltatorch/
License: Apache-2.0
Keywords: delta,torch,pytorch,deltalake
Author: Michael Shtelma
Author-email: mshtelma@gmail.com
Requires-Python: >=3.8,<4.0
Classifier: License :: OSI Approved :: Apache Software License
Classifier: Programming Language :: Python :: 3
Classifier: Programming Language :: Python :: 3.8
Classifier: Programming Language :: Python :: 3.9
Classifier: Programming Language :: Python :: 3.10
Classifier: Programming Language :: Python :: 3.11
Requires-Dist: deltalake (>=0.12.0)
Requires-Dist: evalidate (>=2.0.2)
Requires-Dist: pillow (>=9.5)
